sleepless/__init__.py
sleepless/configs/__init__.py
sleepless/configs/datasets/__init__.py
sleepless/configs/datasets/EDF/__init__.py
sleepless/configs/datasets/EDF/sc_filtered.py
sleepless/configs/datasets/EDF/sc_filtered_crop_wake.py
sleepless/configs/datasets/EDF/sc_unfiltered.py
sleepless/configs/datasets/EDF/st_filtered.py
sleepless/configs/datasets/EDF/st_testing.py
sleepless/configs/datasets/EDF/st_unfiltered.py
sleepless/configs/datasets/EDF/train_sc_filtered.py
sleepless/configs/datasets/EDF/train_st_filtered.py
sleepless/configs/datasets/EDF/train_st_sc_filtered.py
sleepless/configs/datasets/EDF_X_MASS/__init__.py
sleepless/configs/datasets/EDF_X_MASS/train_edf_sc.py
sleepless/configs/datasets/EDF_X_MASS/train_edf_sc_crop_wake.py
sleepless/configs/datasets/EDF_X_MASS/train_edf_st.py
sleepless/configs/datasets/EDF_X_MASS/train_edf_st_sc.py
sleepless/configs/datasets/EDF_X_MASS/train_mass_ss3.py
sleepless/configs/datasets/MASS/__init__.py
sleepless/configs/datasets/MASS/ss1_subset.py
sleepless/configs/datasets/MASS/ss2_subset.py
sleepless/configs/datasets/MASS/ss3_filtered_fpz_cz.py
sleepless/configs/datasets/MASS/ss3_unfiltered_fpz_cz.py
sleepless/configs/datasets/MASS/ss4_subset.py
sleepless/configs/datasets/MASS/ss5_subset.py
sleepless/configs/datasets/mixed_all_db/__init__.py
sleepless/configs/datasets/mixed_all_db/mixed_all_db.py
sleepless/configs/grid_search/__init__.py
sleepless/configs/grid_search/gbc.py
sleepless/configs/grid_search/randomforest.py
sleepless/configs/grid_search/xgboost.py
sleepless/configs/models/__init__.py
sleepless/configs/models_and_models_parameters/__init__.py
sleepless/configs/models_and_models_parameters/blanco_baseline/blanco.py
sleepless/configs/models_and_models_parameters/chambon2018_baseline/__init__.py
sleepless/configs/models_and_models_parameters/chambon2018_baseline/chambon2018.py
sleepless/configs/models_and_models_parameters/chambon2018_baseline/chambon2018_noscheduler.py
sleepless-2.0.1.dist-info/METADATA
sleepless-2.0.1.dist-info/WHEEL
sleepless-2.0.1.dist-info/entry_points.txt
sleepless-2.0.1.dist-info/top_level.txt
sleepless-2.0.1.dist-info/zip-safe
sleepless-2.0.1.dist-info/RECORD
